admission/__init__.py
admission/interface.py
admission/rules_rag_read.py
ajt_grounded_extract-2.1.0.dist-info/licenses/LICENSE
audit/__init__.py
audit/intent_detector.py
audit/reason_map.py
engine/__init__.py
engine/archive.py
engine/audit.py
engine/extract.py
engine/ground.py
engine/ingest.py
engine/judge.py
engine/pipeline.py
execution/__init__.py
execution/rag_read_gate.py
execution/retriever.py
execution/token_validator.py
ajt_grounded_extract-2.1.0.dist-info/METADATA
ajt_grounded_extract-2.1.0.dist-info/WHEEL
ajt_grounded_extract-2.1.0.dist-info/top_level.txt
ajt_grounded_extract-2.1.0.dist-info/RECORD
