Metadata-Version: 2.4
Name: ajt-grounded-extract
Version: 2.1.0
Summary: Judgment-first grounded extraction engine. Returns ACCEPT with evidence or STOP with proof. Nothing in between.
Home-page: https://github.com/Nick-heo-eg/ajt-grounded-extract
Author: AJT Contributors
Author-email: 
License: MIT
Project-URL: Homepage, https://github.com/Nick-heo-eg/ajt-grounded-extract
Project-URL: Documentation, https://github.com/Nick-heo-eg/ajt-grounded-extract/blob/main/README.md
Project-URL: Repository, https://github.com/Nick-heo-eg/ajt-grounded-extract
Project-URL: Attack Tests, https://github.com/Nick-heo-eg/ajt-grounded-extract/blob/main/ATTACK_TEST.md
Project-URL: Constitution, https://github.com/Nick-heo-eg/ajt-grounded-extract/blob/main/ADMISSION_CONSTITUTION.md
Keywords: audit,compliance,legal,extraction,stop-first,negative-proof
Classifier: Development Status :: 5 - Production/Stable
Classifier: Intended Audience :: Developers
Classifier: Intended Audience :: Legal Industry
Classifier: License :: OSI Approved :: MIT License
Classifier: Programming Language :: Python :: 3
Requires-Python: >=3.7
License-File: LICENSE
Dynamic: home-page
Dynamic: license-file
Dynamic: requires-python
